{"_id":"60b6e9c91ec85acb4193cdc2","sets":[{"_id":"61954db1a48a6ff6cf3e07ef","artifactSets":[{"_id":"60b6e9c91ec85acb4193cdc2","activation_number":4}],"total":57181,"battleCount":143566,"winCount":127376,"avgStar":2.861903236142262},{"_id":"61954db5a48a6ff6cf3e09d2","artifactSets":[{"_id":"60b6e9c91ec85acb4193cdc2","activation_number":2}],"total":2416,"battleCount":2267,"winCount":1981,"avgStar":2.8447287163652404},{"_id":"61954db5a48a6ff6cf3e0b00","artifactSets":[{"_id":"60b6e9c91ec85acb4193cdc2","activation_number":2},{"_id":"60b6e9c91ec85acb4193cca6","activation_number":2}],"total":4213,"battleCount":6433,"winCount":5679,"avgStar":2.8580755479558526},{"_id":"61954db6a48a6ff6cf3e0b7e","artifactSets":[{"_id":"60b6e9c91ec85acb4193cdc2","activation_number":2},{"_id":"60b6e9c91ec85acb4193cc4e","activation_number":2}],"total":4447,"battleCount":4824,"winCount":4260,"avgStar":2.854684908789386},{"_id":"61954db8a48a6ff6cf3e0eec","artifactSets":[{"_id":"60b6e9ca1ec85acb4193d041","activation_number":2},{"_id":"60b6e9c91ec85acb4193cdc2","activation_number":2}],"total":644,"battleCount":812,"winCount":690,"avgStar":2.8201970443349755},{"_id":"61954dbba48a6ff6cf3e119f","artifactSets":[{"_id":"60b6e9c91ec85acb4193cf13","activation_number":2},{"_id":"60b6e9c91ec85acb4193cdc2","activation_number":2}],"total":50,"battleCount":97,"winCount":80,"avgStar":2.7938144329896906},{"_id":"61954dbca48a6ff6cf3e1334","artifactSets":[{"_id":"60f897d6c582ef2754bbebe1","activation_number":2},{"_id":"60b6e9c91ec85acb4193cdc2","activation_number":2}],"total":697,"battleCount":794,"winCount":706,"avgStar":2.86272040302267},{"_id":"61954dbea48a6ff6cf3e1590","artifactSets":[{"_id":"60f8c761c582ef2754c6afd3","activation_number":2},{"_id":"60b6e9c91ec85acb4193cdc2","activation_number":2}],"total":192,"battleCount":215,"winCount":189,"avgStar":2.855813953488372},{"_id":"61954dcea48a6ff6cf3e27a8","artifactSets":[{"_id":"60b6e9c91ec85acb4193cdc2","activation_number":2},{"_id":"60b6e9c91ec85acb4193cc93","activation_number":2}],"total":74,"battleCount":36,"winCount":31,"avgStar":2.8333333333333335},{"_id":"61954ddba48a6ff6cf3e34cb","artifactSets":[{"_id":"60b6e9c91ec85acb4193cdc2","activation_number":2},{"_id":"60b6e9c91ec85acb4193cc81","activation_number":2}],"total":211,"battleCount":347,"winCount":290,"avgStar":2.8126801152737753},{"_id":"61954de7a48a6ff6cf3e41f1","artifactSets":[{"_id":"60b6e9c91ec85acb4193cf3d","activation_number":2},{"_id":"60b6e9c91ec85acb4193cdc2","activation_number":2}],"total":274,"battleCount":267,"winCount":221,"avgStar":2.790262172284644},{"_id":"61954df4a48a6ff6cf3e4e3c","artifactSets":[{"_id":"60b6e9fd1ec85acb4193e2e7","activation_number":2},{"_id":"60b6e9c91ec85acb4193cdc2","activation_number":2}],"total":192,"battleCount":185,"winCount":150,"avgStar":2.7621621621621624},{"_id":"61954e14a48a6ff6cf3e6d86","artifactSets":[{"_id":"60b6ea101ec85acb4193ed80","activation_number":2},{"_id":"60b6e9c91ec85acb4193cdc2","activation_number":2}],"total":31,"battleCount":7,"winCount":7,"avgStar":3},{"_id":"61954ed1a48a6ff6cf3ef400","artifactSets":[{"_id":"60b6e9c91ec85acb4193cdc2","activation_number":2},{"_id":"60b6e9c91ec85acb4193cc85","activation_number":2}],"total":26,"battleCount":27,"winCount":25,"avgStar":2.925925925925926},{"_id":"61954ee1a48a6ff6cf3efd38","artifactSets":[{"_id":"60b6eedb1ec85acb4195e658","activation_number":2},{"_id":"60b6e9c91ec85acb4193cdc2","activation_number":2}],"total":16,"battleCount":9,"winCount":4,"avgStar":2.3333333333333335},{"_id":"61954ee7a48a6ff6cf3f00a0","artifactSets":[{"_id":"60b6ea101ec85acb4193ed4f","activation_number":2},{"_id":"60b6e9c91ec85acb4193cdc2","activation_number":2}],"total":12,"battleCount":16,"winCount":14,"avgStar":2.875},{"_id":"6195505ea48a6ff6cf3fea0c","artifactSets":[{"_id":"60b6e9c91ec85acb4193cdc2","activation_number":2},{"_id":"60b6e9c91ec85acb4193cc75","activation_number":2}],"total":20,"battleCount":9,"winCount":6,"avgStar":2.5555555555555554},{"_id":"6195513ba48a6ff6cf407d3e","artifactSets":[{"_id":"60b6e9c91ec85acb4193cdc2","activation_number":2},{"_id":"60b6e9c91ec85acb4193cc4c","activation_number":2}],"total":30,"battleCount":25,"winCount":25,"avgStar":3},{"_id":"6195518da48a6ff6cf40af43","artifactSets":[{"_id":"60b6ec581ec85acb4194cf65","activation_number":2},{"_id":"60b6e9c91ec85acb4193cdc2","activation_number":2}],"total":15,"battleCount":3,"winCount":3,"avgStar":3},{"_id":"61955568a48a6ff6cf432330","artifactSets":[{"_id":"60b6e9c91ec85acb4193cecc","activation_number":2},{"_id":"60b6e9c91ec85acb4193cdc2","activation_number":2}],"total":7,"battleCount":6,"winCount":5,"avgStar":2.8333333333333335}]}